{"dependencies":[{"name":"/home/akiohayakawa/workspace/browser_editor/package.json","includedInParent":true,"mtime":1532065308636},{"name":"/home/akiohayakawa/workspace/browser_editor/node_modules/csvtojson/package.json","includedInParent":true,"mtime":1531826268619}],"generated":{"js":"\"use strict\";function e(e){var r={delimiter:\",\",ignoreColumns:void 0,includeColumns:void 0,quote:'\"',trim:!0,checkType:!1,ignoreEmpty:!1,noheader:!1,headers:void 0,flatKeys:!1,maxRowLength:0,checkColumn:!1,escape:'\"',colParser:{},eol:void 0,alwaysSplitAtEOL:!1,output:\"json\"};for(var o in e||(e={}),e)e.hasOwnProperty(o)&&(Array.isArray(e[o])?r[o]=[].concat(e[o]):r[o]=e[o]);return r}Object.defineProperty(exports,\"__esModule\",{value:!0}),exports.mergeParams=e;"},"hash":"11cd1280603f928b00abbf46d37466c6","cacheData":{"env":{}}}